cloudfiler/AppConfig.py
cloudfiler/CloudConnectDlg.py
cloudfiler/CloudFiler.ini
cloudfiler/CloudFilerUserGuide.pdf
cloudfiler/FileCrypto.py
cloudfiler/FileListCtrl.py
cloudfiler/GetNewLicenseDlg.py
cloudfiler/Licensing.py
cloudfiler/NewCloudDlg.py
cloudfiler/NewFolderDlg.py
cloudfiler/NullLicensing.py
cloudfiler/OutputList.py
cloudfiler/S3FileStore.py
cloudfiler/S3WorkerThread.py
cloudfiler/SettingsDlg.py
cloudfiler/Utils.py
cloudfiler/__init__.py
cloudfiler/__main__.py
cloudfiler/images/CloudFiler.png
cloudfiler/images/app.ico
cloudfiler/images/application-pdf.png
cloudfiler/images/application-x-cd-image.png
cloudfiler/images/application-x-zerosize.png
cloudfiler/images/bullet_arrow_down.png
cloudfiler/images/bullet_arrow_up.png
cloudfiler/images/cd.png
cloudfiler/images/cog.png
cloudfiler/images/css.png
cloudfiler/images/document-open-folder.png
cloudfiler/images/document-open-remote.png
cloudfiler/images/emblem-question.png
cloudfiler/images/excel.png
cloudfiler/images/film.png
cloudfiler/images/go-next-2.png
cloudfiler/images/go-up-5.png
cloudfiler/images/help-contents-5.png
cloudfiler/images/help.png
cloudfiler/images/icon_sources.txt
cloudfiler/images/image.png
cloudfiler/images/link.png
cloudfiler/images/lock.png
cloudfiler/images/music.png
cloudfiler/images/package.png
cloudfiler/images/page_link.png
cloudfiler/images/page_world.png
cloudfiler/images/pictogram-din-m000-general.png
cloudfiler/images/pictogram-din-w000-general.png
cloudfiler/images/powerpoint.png
cloudfiler/images/script_gear.png
cloudfiler/images/shield_green.png
cloudfiler/images/shield_red.png
cloudfiler/images/text-x-dtd.png
cloudfiler/images/text-x-python.png
cloudfiler/images/text_align_left.png
cloudfiler/images/text_signature.png
cloudfiler/images/word.png
cloudfiler-2.0.42.dist-info/DESCRIPTION.rst
cloudfiler-2.0.42.dist-info/METADATA
cloudfiler-2.0.42.dist-info/RECORD
cloudfiler-2.0.42.dist-info/WHEEL
cloudfiler-2.0.42.dist-info/metadata.json
cloudfiler-2.0.42.dist-info/top_level.txt
